setup.py
avilabsutils/__init__.py
avilabsutils/cloud.py
avilabsutils/csv_parser.py
avilabsutils/decorators.py
avilabsutils/json_converter.py
avilabsutils/messenger.py
avilabsutils/paths.py
avilabsutils/printer.py
avilabsutils.egg-info/PKG-INFO
avilabsutils.egg-info/SOURCES.txt
avilabsutils.egg-info/dependency_links.txt
avilabsutils.egg-info/requires.txt
avilabsutils.egg-info/top_level.txt
avilabsutils/data/__init__.py
avilabsutils/data/data_session.py
avilabsutils/data/data_table.py
avilabsutils/data/data_view.py
avilabsutils/data/row.py