Metadata-Version: 1.1
Name: avilabsutils
Version: 1.2.1
Summary: Common utilities used by Avilay Labs
Home-page: https://bitbucket.org/avilay/utils
Author: Avilay Parekh
Author-email: avilay@avilaylabs.net
License: MIT
Platform: UNKNOWN
Classifier: Development Status :: 5 - Production/Stable
Classifier: Intended Audience :: Developers
Classifier: License :: OSI Approved :: MIT License
Classifier: Programming Language :: Python :: 3.4
Classifier: Programming Language :: Python :: 3.5
